{
	"folders": {},
	"connections": {
		"derby-17d241c9def-dcb5f0b0387408b": {
			"provider": "generic",
			"driver": "derby",
			"name": "ipint-tp2-entreprise",
			"save-password": true,
			"read-only": false,
			"configuration": {
				"database": "D:\\M2_MIAGE\\ARI\\databases\\ipint-tp2-entreprise",
				"url": "jdbc:derby:D:\\M2_MIAGE\\ARI\\databases\\ipint-tp2-entreprise",
				"type": "dev",
				"auth-model": "native",
				"handlers": {}
			}
		}
	},
	"connection-types": {
		"dev": {
			"name": "Development",
			"color": "255,255,255",
			"description": "Regular development database",
			"auto-commit": true,
			"confirm-execute": false,
			"confirm-data-change": false,
			"auto-close-transactions": false
		}
	}
}